{
  "project_info": {
    "project_number": "914738348240",
    "project_id": "menugrid-otp",
    "storage_bucket": "menugrid-otp.firebasestorage.app"
  },
  "client": [
    {
      "client_info": {
        "mobilesdk_app_id": "1:914738348240:android:3bbedb80e2aa4d5c959ed5",
        "android_client_info": {
          "package_name": "com.menugrid"
        }
      },
      "oauth_client": [],
      "api_key": [
        {
          "current_key": "AIzaSyCRKLpB8bqbcgh_ckhUMDgL8KdMU0oQZuE"
        }
      ],
      "services": {
        "appinvite_service": {
          "other_platform_oauth_client": []
        }
      }
    }
  ],
  "configuration_version": "1"
}